[
  {
    "full_name": "emad-elsaid/xlog",
    "stargazers_count": 27,
    "open_issues_count": 1,
    "forks_count": 0
  },
  {
    "full_name": "BuilderIO/qwik",
    "stargazers_count": 12991,
    "open_issues_count": 201,
    "forks_count": 535
  },
  {
    "full_name": "Lodennn/Kinetic",
    "stargazers_count": 1,
    "open_issues_count": 1,
    "forks_count": 1
  },
  {
    "full_name": "dortania/OpenCore-Install-Guide",
    "stargazers_count": 2978,
    "open_issues_count": 10,
    "forks_count": 546
  },
  {
    "full_name": "suren-atoyan/monaco-react",
    "stargazers_count": 2127,
    "open_issues_count": 61,
    "forks_count": 156
  },
  {
    "full_name": "simplelocalize/simplelocalize-next-translate",
    "stargazers_count": 2,
    "open_issues_count": 0,
    "forks_count": 1
  },
  {
    "full_name": "sealninja/react-ssr-example",
    "stargazers_count": 33,
    "open_issues_count": 1,
    "forks_count": 21
  },
  {
    "full_name": "googleapis/nodejs-translate",
    "stargazers_count": 507,
    "open_issues_count": 15,
    "forks_count": 129
  },
  {
    "full_name": "DenverCoder1/readme-typing-svg",
    "stargazers_count": 1751,
    "open_issues_count": 6,
    "forks_count": 332
  },
  {
    "full_name": "Anirban-1490/Downlist",
    "stargazers_count": 7,
    "open_issues_count": 2,
    "forks_count": 0
  },
  {
    "full_name": "pacoita/modern-web",
    "stargazers_count": 12,
    "open_issues_count": 0,
    "forks_count": 3
  },
  {
    "full_name": "Ahmed-Elswerky/react-flying-item",
    "stargazers_count": 1,
    "open_issues_count": 0,
    "forks_count": 0
  },
  {
    "full_name": "iamkun/dayjs",
    "stargazers_count": 41180,
    "open_issues_count": 592,
    "forks_count": 2058
  },
  {
    "full_name": "hail2u/html-best-practices",
    "stargazers_count": 3476,
    "open_issues_count": 3,
    "forks_count": 380
  },
  {
    "full_name": "tycrek/degoogle",
    "stargazers_count": 6452,
    "open_issues_count": 47,
    "forks_count": 307
  },
  {
    "full_name": "berthubert/googerteller",
    "stargazers_count": 1996,
    "open_issues_count": 16,
    "forks_count": 103
  },
  {
    "full_name": "react-hook-form/react-hook-form",
    "stargazers_count": 31568,
    "open_issues_count": 7,
    "forks_count": 1570
  },
  {
    "full_name": "lucidrains/imagen-pytorch",
    "stargazers_count": 5583,
    "open_issues_count": 48,
    "forks_count": 490
  },
  {
    "full_name": "open-sauced/open-sauced",
    "stargazers_count": 805,
    "open_issues_count": 9,
    "forks_count": 431
  },
  {
    "full_name": "WebDevSimplified/Noob-Vs-Pro-Code",
    "stargazers_count": 142,
    "open_issues_count": 2,
    "forks_count": 58
  },
  {
    "full_name": "sharafa839/Baladna",
    "stargazers_count": 1,
    "open_issues_count": 0,
    "forks_count": 0
  },
  {
    "full_name": "udacity/reactnd-chirper-app",
    "stargazers_count": 47,
    "open_issues_count": 4,
    "forks_count": 442
  },
  {
    "full_name": "Ahmed-Elswerky/custom-tampermonkey-scripts",
    "stargazers_count": 4,
    "open_issues_count": 0,
    "forks_count": 0
  },
  {
    "full_name": "transistorsoft/flutter_background_fetch",
    "stargazers_count": 502,
    "open_issues_count": 24,
    "forks_count": 138
  },
  {
    "full_name": "udacity/reactnd-project-myreads-starter",
    "stargazers_count": 243,
    "open_issues_count": 27,
    "forks_count": 3639
  },
  {
    "full_name": "udacity/reactnd-contacts-app",
    "stargazers_count": 110,
    "open_issues_count": 6,
    "forks_count": 607
  },
  {
    "full_name": "basarat/coding-interview",
    "stargazers_count": 39,
    "open_issues_count": 0,
    "forks_count": 1
  },
  {
    "full_name": "OsamaYousry/We-Usage-Statistics",
    "stargazers_count": 13,
    "open_issues_count": 0,
    "forks_count": 1
  },
  {
    "full_name": "andrey-ushakov/esc_pos_utils",
    "stargazers_count": 92,
    "open_issues_count": 61,
    "forks_count": 137
  },
  {
    "full_name": "andrey-ushakov/esc_pos_printer",
    "stargazers_count": 250,
    "open_issues_count": 72,
    "forks_count": 207
  }
]